nautobot_consumables/__init__.py
nautobot_consumables/api/__init__.py
nautobot_consumables/api/serializers.py
nautobot_consumables/api/urls.py
nautobot_consumables/api/views.py
nautobot_consumables/fields.py
nautobot_consumables/filter_extensions.py
nautobot_consumables/filters.py
nautobot_consumables/forms.py
nautobot_consumables/management/__init__.py
nautobot_consumables/management/commands/__init__.py
nautobot_consumables/management/commands/create_consumables_env.py
nautobot_consumables/management/commands/flush_consumables_env.py
nautobot_consumables/migrations/0001_initial.py
nautobot_consumables/migrations/0002_alter_models_for_v2.py
nautobot_consumables/migrations/__init__.py
nautobot_consumables/models.py
nautobot_consumables/navigation.py
nautobot_consumables/signals.py
nautobot_consumables/static/nautobot_consumables/css/colors.css
nautobot_consumables/static/nautobot_consumables/docs/404.html
nautobot_consumables/static/nautobot_consumables/docs/admin/compatibility_matrix.html
nautobot_consumables/static/nautobot_consumables/docs/admin/install.html
nautobot_consumables/static/nautobot_consumables/docs/admin/release_notes/index.html
nautobot_consumables/static/nautobot_consumables/docs/admin/release_notes/version_1.0.html
nautobot_consumables/static/nautobot_consumables/docs/admin/release_notes/version_2.0.html
nautobot_consumables/static/nautobot_consumables/docs/admin/uninstall.html
nautobot_consumables/static/nautobot_consumables/docs/admin/upgrade.html
nautobot_consumables/static/nautobot_consumables/docs/assets/_mkdocstrings.css
nautobot_consumables/static/nautobot_consumables/docs/assets/favicon.ico
nautobot_consumables/static/nautobot_consumables/docs/assets/images/favicon.png
nautobot_consumables/static/nautobot_consumables/docs/assets/javascripts/bundle.83f73b43.min.js
nautobot_consumables/static/nautobot_consumables/docs/assets/javascripts/bundle.83f73b43.min.js.map
nautobot_consumables-2.0.1.dist-info/LICENSE
nautobot_consumables-2.0.1.dist-info/METADATA
nautobot_consumables-2.0.1.dist-info/WHEEL
nautobot_consumables-2.0.1.dist-info/RECORD
