Metadata-Version: 2.1
Name: nautobot-consumables
Version: 2.0.1
Summary: Consumables Tracking for Nautobot
Home-page: https://github.com/NVIDIA/nautobot-app-consumables
License: Apache-2.0
Keywords: nautobot,nautobot-app,nautobot-plugin
Author: Mark Troyer
Author-email: mtroyer@nvidia.com
Maintainer: Mark Troyer
Maintainer-email: mtroyer@nvidia.com
Requires-Python: >=3.10,<3.13
Classifier: License :: OSI Approved :: Apache Software License
Classifier: Programming Language :: Python :: 3
Classifier: Programming Language :: Python :: 3.10
Classifier: Programming Language :: Python :: 3.11
Classifier: Programming Language :: Python :: 3.12
Requires-Dist: nautobot (>=2.0.0,<3.0.0)
Project-URL: Repository, https://github.com/NVIDIA/nautobot-app-consumables
